samssimplescraper/__init__.py
samssimplescraper/scraper.py
samssimplescraper/sitemapscraper.py
samssimplescraper-0.1.3.dist-info/LICENSE
samssimplescraper-0.1.3.dist-info/METADATA
samssimplescraper-0.1.3.dist-info/WHEEL
samssimplescraper-0.1.3.dist-info/top_level.txt
samssimplescraper-0.1.3.dist-info/RECORD
