Metadata-Version: 2.1
Name: samssimplescraper
Version: 0.1.3
Summary: tool to help scrape sitemaps and the links they scrape
Home-page: https://github.com/samueladamsmcguire/simplescraper
Author: Samuel McGuire
Author-email: samuelmcguire@engineer.com
License: MIT
Platform: UNKNOWN
Classifier: Programming Language :: Python :: 3.8
Requires-Dist: beautifulsoup4
Requires-Dist: tqdm
